skipperz/__init__.py
skipperz/__main__.py
skipperz/game.py
skipperz/main_loop.py
skipperz/params.py
skipperz/FX/basic_screen_fx.py
skipperz/FX/dwingling_stars.py
skipperz/FX/sound.py
skipperz/FX/tileArray.py
skipperz/assets/(Dune)ECOLOVE.mod
skipperz/assets/218721__bareform__boom-bang.aiff
skipperz/assets/535592__xhale303__boom-impact-2.mp3
skipperz/assets/58765__suonho__basscapes-ultralowend.wav
skipperz/assets/BoumA1.png
skipperz/assets/BoumA2.png
skipperz/assets/BoumA3.png
skipperz/assets/Hubble_ultra_deep.png
skipperz/assets/Nebulus.mod
skipperz/assets/Raleway-VariableFont_wght.ttf
skipperz/assets/alien.mod
skipperz/assets/bluesong.mod
skipperz/assets/condom corruption.mod
skipperz/assets/drone.mp3
skipperz/assets/external ressources.md
skipperz/assets/malabar.mod
skipperz/assets/mechant1-c.png
skipperz/assets/mechant2-c.png
skipperz/assets/mechant3-c.png
skipperz/assets/mechant4-c.png
skipperz/assets/mechant5-c.png
skipperz/assets/spaceship-2135750_165.png
skipperz/assets/spaceships-155165__340.png
skipperz/assets/tir1.mp3
skipperz/levels/enchainement.py
skipperz/levels/level.py
skipperz/levels/level_1.py
skipperz/levels/level_2.py
skipperz/pgSprite/mobile.py
skipperz/pgSprite/pgSprite.py
skipperz/pgSprite/vector2d.py
skipperz/skip_libs/badGuys.py
skipperz/skip_libs/credit_screen.py
skipperz/skip_libs/pgThrotle.py
skipperz/skip_libs/pgZoneText.py
skipperz/skip_libs/raster.py
skipperz-2.0.6.dist-info/LICENSE
skipperz-2.0.6.dist-info/METADATA
skipperz-2.0.6.dist-info/WHEEL
skipperz-2.0.6.dist-info/top_level.txt
skipperz-2.0.6.dist-info/RECORD
