Metadata-Version: 2.1
Name: skipperz
Version: 2.0.6
Summary: A game where you skip incoming spaceships. Lateral scroll
Home-page: https://bitbucket.org/holypython/skipper/src/master/
Author: Simon Zozol
Author-email: simon.zozol@gmail.com
Classifier: Topic :: Games/Entertainment :: Side-Scrolling/Arcade Games
Classifier: Programming Language :: Python :: 3.6
Classifier: License :: CC0 1.0 Universal (CC0 1.0) Public Domain Dedication
Classifier: Operating System :: OS Independent
Classifier: Development Status :: 4 - Beta
Requires-Python: >=3.6
License-File: LICENSE
Requires-Dist: pygame (>=2)
Requires-Dist: numpy
Requires-Dist: pygame-menu
